td_install/__init__.py
td_install/__main__.py
td_install/imagepig.py
td_install/install.py
td_install/nwjs.py
td_install/steam.py
td_install/task.py
td_install/test.patch
td_install-0.0.2.dist-info/LICENSE.txt
td_install-0.0.2.dist-info/METADATA
td_install-0.0.2.dist-info/RECORD
td_install-0.0.2.dist-info/WHEEL
td_install-0.0.2.dist-info/entry_points.txt
td_install-0.0.2.dist-info/top_level.txt
