Metadata-Version: 2.1
Name: td-install
Version: 0.0.2
Summary: Tokyo Dark macOS port creation tool.
Home-page: https://github.com/FrederickGeek8/td_install
Author: Frederick Morlock
Author-email: FrederickGeek8@gmail.com
License: MIT License
Platform: MacOS X
Classifier: Programming Language :: Python :: 2
Classifier: Programming Language :: Python :: 3
Classifier: License :: OSI Approved :: MIT License
Classifier: Operating System :: MacOS :: MacOS X
Classifier: Environment :: MacOS X
Requires-Dist: future
Requires-Dist: patch (==1.*)
Requires-Dist: progressbar2
